rawtimer/__init__.py
rawtimer/timer.py
rawtimer-0.0.0.dist-info/licenses/LICENSE
rawtimer-0.0.0.dist-info/METADATA
rawtimer-0.0.0.dist-info/WHEEL
rawtimer-0.0.0.dist-info/top_level.txt
rawtimer-0.0.0.dist-info/RECORD
