Metadata-Version: 2.4
Name: rawtimer
Version: 0.0.0
Summary: A simple timer manager.
Author-email: GGN_2015 <neko@jlulug.org>
License-Expression: MIT
Requires-Python: >=3.10
License-File: LICENSE
Dynamic: license-file
